openpy_fxts/__init__.py
openpy_fxts/architectures/__init__.py
openpy_fxts/architectures/baseline_arch.py
openpy_fxts/architectures/dp_models.py
openpy_fxts/architectures/function.py
openpy_fxts/architectures/fxts/__init__.py
openpy_fxts/architectures/fxts/arch_dicts.py
openpy_fxts/architectures/fxts/fxts_mdls.py
openpy_fxts/architectures/fxts/hybrids/__init__.py
openpy_fxts/architectures/fxts/hybrids/BiRNN_others.py
openpy_fxts/architectures/fxts/hybrids/Conv1D_others.py
openpy_fxts/architectures/fxts/hybrids/EncDec_hybrids.py
openpy_fxts/architectures/fxts/hybrids/Others.py
openpy_fxts/architectures/fxts/hybrids/seq2seq/__init__.py
openpy_fxts/architectures/fxts/hybrids/seq2seq/decoder_mdl.py
openpy_fxts/architectures/fxts/hybrids/seq2seq/encoder_mdl.py
openpy_fxts/architectures/fxts/hybrids/seq2seq/Hybrids.py
openpy_fxts/architectures/fxts/simple/__init__.py
openpy_fxts/architectures/fxts/simple/Conv1D_class.py
openpy_fxts/architectures/fxts/simple/MLP_class.py
openpy_fxts/architectures/fxts/simple/RNN_class.py
openpy_fxts/architectures/get_arch_mdls.py
openpy_fxts/architectures/layers/__init__.py
openpy_fxts/architectures/layers/attention_class.py
openpy_fxts/architectures/layers/layers_class.py
openpy_fxts/architectures/mdits/__init__.py
openpy_fxts/architectures/mdits/arch_dicts.py
openpy_fxts/architectures/mdits/hybrids/__init__.py
openpy_fxts/architectures/mdits/hybrids/Attention_class.py
openpy_fxts/architectures/mdits/hybrids/BiRNN_others.py
openpy_fxts/architectures/mdits/hybrids/class_mdls/__init__.py
openpy_fxts/architectures/mdits/hybrids/class_mdls/BiLSTM_others.py
openpy_fxts/architectures/mdits/hybrids/class_mdls/Conv1D_others.py
openpy_fxts/architectures/mdits/hybrids/class_mdls/GRU_others.py
openpy_fxts/architectures/mdits/hybrids/class_mdls/LSTM_others.py
openpy_fxts/architectures/mdits/hybrids/class_mdls/Others.py
openpy_fxts/architectures/mdits/hybrids/class_mdls/Seq2Seq/__init__.py
openpy_fxts-0.2.5.dist-info/LICENSE.md
openpy_fxts-0.2.5.dist-info/METADATA
openpy_fxts-0.2.5.dist-info/WHEEL
openpy_fxts-0.2.5.dist-info/RECORD
