Metadata-Version: 2.1
Name: openpy-fxts
Version: 0.2.5
Summary: Various functions and classes for time series forecasting with Machine and Deep Learning
License: LICENSE.md
Author: Jorge Lara
Author-email: jlara@iee.unsj.edu.ar
Requires-Python: >=3.10,<4.0
Classifier: License :: Other/Proprietary License
Classifier: Programming Language :: Python :: 3
Classifier: Programming Language :: Python :: 3.10
Classifier: Programming Language :: Python :: 3.11
Classifier: Programming Language :: Python :: 3.12
Requires-Dist: build (==1.0.3)
Requires-Dist: cachecontrol (==0.13.1)
Requires-Dist: certifi (==2023.11.17)
Requires-Dist: charset-normalizer (==3.3.2)
Requires-Dist: cleo (==2.1.0)
Requires-Dist: colorama (==0.4.6)
Requires-Dist: contourpy (==1.2.0)
Requires-Dist: crashtest (==0.4.1)
Requires-Dist: cycler (==0.12.1)
Requires-Dist: distlib (==0.3.8)
Requires-Dist: docutils (==0.20.1)
Requires-Dist: dulwich (==0.21.7)
Requires-Dist: fastjsonschema (==2.19.1)
Requires-Dist: filelock (==3.13.1)
Requires-Dist: fonttools (==4.47.2)
Requires-Dist: h5py (==3.10.0)
Requires-Dist: idna (==3.6)
Requires-Dist: importlib-metadata (==7.0.1)
Requires-Dist: installer (==0.7.0)
Requires-Dist: jaraco-classes (==3.3.0)
Requires-Dist: joblib (==1.3.2)
Requires-Dist: keyring (==24.3.0)
Requires-Dist: kiwisolver (==1.4.5)
Requires-Dist: llvmlite (==0.41.1)
Requires-Dist: markdown-it-py (==3.0.0)
Requires-Dist: matplotlib (==3.8.2)
Requires-Dist: mdurl (==0.1.2)
Requires-Dist: minisom (==2.3.1)
Requires-Dist: more-itertools (==10.2.0)
Requires-Dist: msgpack (==1.0.7)
Requires-Dist: nh3 (==0.2.15)
Requires-Dist: numba (==0.58.1)
Requires-Dist: numpy (==1.26.3)
Requires-Dist: packaging (==23.2)
Requires-Dist: pandas (==2.2.0)
Requires-Dist: patsy (==0.5.6)
Requires-Dist: pexpect (==4.9.0)
Requires-Dist: pillow (==10.2.0)
Requires-Dist: pkginfo (==1.9.6)
Requires-Dist: platformdirs (==3.11.0)
Requires-Dist: poetry (==1.7.1)
Requires-Dist: poetry-core (==1.8.1)
Requires-Dist: poetry-plugin-export (==1.6.0)
Requires-Dist: ptyprocess (==0.7.0)
Requires-Dist: pygments (==2.17.2)
Requires-Dist: pyparsing (==3.1.1)
Requires-Dist: pyproject-hooks (==1.0.0)
Requires-Dist: python-dateutil (==2.8.2)
Requires-Dist: pytz (==2023.3.post1)
Requires-Dist: pywin32-ctypes (==0.2.2)
Requires-Dist: rapidfuzz (==3.6.1)
Requires-Dist: readme-renderer (==42.0)
Requires-Dist: requests (==2.31.0)
Requires-Dist: requests-toolbelt (==1.0.0)
Requires-Dist: rfc3986 (==2.0.0)
Requires-Dist: rich (==13.7.0)
Requires-Dist: scikit-learn (==1.4.0)
Requires-Dist: scipy (==1.12.0)
Requires-Dist: seaborn (==0.13.1)
Requires-Dist: shellingham (==1.5.4)
Requires-Dist: six (==1.16.0)
Requires-Dist: statsmodels (==0.14.1)
Requires-Dist: threadpoolctl (==3.2.0)
Requires-Dist: tomli (==2.0.1)
Requires-Dist: tomlkit (==0.12.3)
Requires-Dist: tqdm (==4.66.1)
Requires-Dist: trove-classifiers (==2024.1.8)
Requires-Dist: tslearn (==0.6.3)
Requires-Dist: twine (==4.0.2)
Requires-Dist: tzdata (==2023.4)
Requires-Dist: urllib3 (==2.1.0)
Requires-Dist: virtualenv (==20.25.0)
Requires-Dist: yellowbrick (==1.5)
Requires-Dist: zipp (==3.17.0)
